MANIFEST.in
README.md
rippletxt.py
setup.py
rippletxt.egg-info/PKG-INFO
rippletxt.egg-info/SOURCES.txt
rippletxt.egg-info/dependency_links.txt
rippletxt.egg-info/top_level.txt