Metadata-Version: 1.1
Name: rippletxt
Version: 1.0
Summary: Parser for ripple.txt files
Home-page: https://github.com/miracle2k/rippletxt
Author: Michael Elsdörfer
Author-email: michael@elsdoerfer.com
License: BSD
Platform: UNKNOWN
Classifier: Development Status :: 5 - Production/Stable
Classifier: Intended Audience :: Developers
Classifier: License :: OSI Approved :: BSD License
Classifier: Operating System :: OS Independent
Classifier: Programming Language :: Python
Classifier: Programming Language :: Python :: 3
